{"type":"일반","code":"487830","data":{"별도":{"PL":[{"year":2024,"quarter":4,"label":"2024.4Q","매출액":0.0,"영업이익":-28299118.0,"매출총이익":null,"판매비와관리비":null,"당기순이익":-16810878.0,"계속사업 당기순이익":null,"중단사업 당기순이익":null,"이자비용 등":28813328.0,"법인세":-4441812.0},{"year":2025,"quarter":1,"label":"2025.1Q","매출액":null,"영업이익":-19975710.0,"매출총이익":null,"판매비와관리비":null,"당기순이익":21729078.0,"계속사업 당기순이익":null,"중단사업 당기순이익":null,"이자비용 등":14170489.0,"법인세":5741312.0},{"year":2025,"quarter":2,"label":"2025.2Q","매출액":null,"영업이익":-10546000.0,"매출총이익":null,"판매비와관리비":null,"당기순이익":53029677.0,"계속사업 당기순이익":null,"중단사업 당기순이익":null,"이자비용 등":14327939.0,"법인세":14011633.0},{"year":2025,"quarter":3,"label":"2025.3Q","매출액":null,"영업이익":-11498960.0,"매출총이익":null,"판매비와관리비":null,"당기순이익":28810068.0,"계속사업 당기순이익":null,"중단사업 당기순이익":null,"이자비용 등":15057696.0,"법인세":7612270.0}],"BS":[{"year":2024,"quarter":4,"label":"2024.4Q","자산총계":9854814218.0,"부채총계":1528357568.0,"자본총계":8326456650.0},{"year":2025,"quarter":1,"label":"2025.1Q","자산총계":9908869317.0,"부채총계":1560683589.0,"자본총계":8348185728.0},{"year":2025,"quarter":2,"label":"2025.2Q","자산총계":9981157346.0,"부채총계":1579941941.0,"자본총계":8401215405.0},{"year":2025,"quarter":3,"label":"2025.3Q","자산총계":10036600530.0,"부채총계":1606575057.0,"자본총계":8430025473.0}],"CF":[{"year":2024,"quarter":4,"label":"2024.4Q","영업활동CF":-26740208.0,"투자활동CF":-9525474952.0,"재무활동CF":9846527260.0,"기초현금":null,"기말현금":null},{"year":2025,"quarter":1,"label":"2025.1Q","영업활동CF":-7501337.0,"투자활동CF":0.0,"재무활동CF":0.0,"기초현금":null,"기말현금":null},{"year":2025,"quarter":2,"label":"2025.2Q","영업활동CF":5638888.0,"투자활동CF":-25056081.0,"재무활동CF":0.0,"기초현금":null,"기말현금":null},{"year":2025,"quarter":3,"label":"2025.3Q","영업활동CF":-7489313.0,"투자활동CF":0.0,"재무활동CF":0.0,"기초현금":null,"기말현금":null}],"Profitability":[{"year":2024,"quarter":4,"label":"2024.4Q","매출액":0.0,"영업이익":-28299118.0,"매출총이익":null,"판매비와관리비":null,"당기순이익":-16810878.0,"계속사업 당기순이익":null,"중단사업 당기순이익":null,"이자비용 등":28813328.0,"법인세":-4441812.0},{"year":2025,"quarter":1,"label":"2025.1Q","매출액":null,"영업이익":-19975710.0,"매출총이익":null,"판매비와관리비":null,"당기순이익":21729078.0,"계속사업 당기순이익":null,"중단사업 당기순이익":null,"이자비용 등":14170489.0,"법인세":5741312.0},{"year":2025,"quarter":2,"label":"2025.2Q","매출액":null,"영업이익":-10546000.0,"매출총이익":null,"판매비와관리비":null,"당기순이익":53029677.0,"계속사업 당기순이익":null,"중단사업 당기순이익":null,"이자비용 등":14327939.0,"법인세":14011633.0},{"year":2025,"quarter":3,"label":"2025.3Q","매출액":null,"영업이익":-11498960.0,"매출총이익":null,"판매비와관리비":null,"당기순이익":28810068.0,"계속사업 당기순이익":null,"중단사업 당기순이익":null,"이자비용 등":15057696.0,"법인세":7612270.0}],"Stability":[{"year":2024,"quarter":4,"label":"2024.4Q","자산총계":9854814218.0,"부채총계":1528357568.0,"자본총계":8326456650.0},{"year":2025,"quarter":1,"label":"2025.1Q","자산총계":9908869317.0,"부채총계":1560683589.0,"자본총계":8348185728.0},{"year":2025,"quarter":2,"label":"2025.2Q","자산총계":9981157346.0,"부채총계":1579941941.0,"자본총계":8401215405.0},{"year":2025,"quarter":3,"label":"2025.3Q","자산총계":10036600530.0,"부채총계":1606575057.0,"자본총계":8430025473.0}]},"연결":{}},"stock_data":[{"date":"2024-11-15","open":2350,"high":2485,"low":2000,"close":2000,"volume":15542236,"marcap":8700000000},{"date":"2024-11-18","open":2005,"high":2015,"low":2000,"close":2005,"volume":336239,"marcap":8721750000},{"date":"2024-11-19","open":2010,"high":2015,"low":2005,"close":2010,"volume":77164,"marcap":8743500000},{"date":"2024-11-20","open":2010,"high":2015,"low":2000,"close":2005,"volume":197791,"marcap":8721750000},{"date":"2024-11-21","open":2005,"high":2015,"low":2000,"close":2010,"volume":37009,"marcap":8743500000},{"date":"2024-11-22","open":2005,"high":2015,"low":2005,"close":2015,"volume":27774,"marcap":8765250000},{"date":"2024-11-25","open":2015,"high":2015,"low":2005,"close":2010,"volume":28258,"marcap":8743500000},{"date":"2024-11-26","open":2010,"high":2015,"low":2005,"close":2015,"volume":5031,"marcap":8765250000},{"date":"2024-11-27","open":2010,"high":2015,"low":2010,"close":2010,"volume":35829,"marcap":8743500000},{"date":"2024-11-28","open":2015,"high":2015,"low":2005,"close":2010,"volume":29719,"marcap":8743500000},{"date":"2024-11-29","open":2010,"high":2015,"low":2000,"close":2010,"volume":40147,"marcap":8743500000},{"date":"2024-12-02","open":2010,"high":2010,"low":2000,"close":2010,"volume":11529,"marcap":8743500000},{"date":"2024-12-03","open":2010,"high":2010,"low":1996,"close":2000,"volume":13422,"marcap":8700000000},{"date":"2024-12-04","open":1997,"high":2005,"low":1997,"close":1999,"volume":31817,"marcap":8695650000},{"date":"2024-12-05","open":2005,"high":2005,"low":2000,"close":2005,"volume":7629,"marcap":8721750000},{"date":"2024-12-06","open":2005,"high":2010,"low":2000,"close":2005,"volume":35030,"marcap":8721750000},{"date":"2024-12-09","open":1996,"high":2005,"low":1994,"close":2005,"volume":11370,"marcap":8721750000},{"date":"2024-12-10","open":2000,"high":2005,"low":1995,"close":2005,"volume":24337,"marcap":8721750000},{"date":"2024-12-11","open":2005,"high":2005,"low":1996,"close":2005,"volume":9160,"marcap":8721750000},{"date":"2024-12-12","open":2000,"high":2000,"low":1993,"close":2000,"volume":38621,"marcap":8700000000},{"date":"2024-12-13","open":2000,"high":2000,"low":1994,"close":1999,"volume":2845,"marcap":8695650000},{"date":"2024-12-16","open":1993,"high":2000,"low":1993,"close":2000,"volume":3294,"marcap":8700000000},{"date":"2024-12-17","open":1999,"high":2000,"low":1994,"close":2000,"volume":12787,"marcap":8700000000},{"date":"2024-12-18","open":2000,"high":2000,"low":1997,"close":2000,"volume":2129,"marcap":8700000000},{"date":"2024-12-19","open":2000,"high":2000,"low":1996,"close":1999,"volume":13636,"marcap":8695650000},{"date":"2024-12-20","open":1999,"high":1999,"low":1994,"close":1994,"volume":10301,"marcap":8673900000},{"date":"2024-12-23","open":1998,"high":1998,"low":1985,"close":1987,"volume":10930,"marcap":8643450000},{"date":"2024-12-24","open":1987,"high":1995,"low":1983,"close":1986,"volume":30721,"marcap":8639100000},{"date":"2024-12-26","open":1986,"high":1988,"low":1978,"close":1987,"volume":16114,"marcap":8643450000},{"date":"2024-12-27","open":1987,"high":1987,"low":1980,"close":1984,"volume":2280,"marcap":8630400000},{"date":"2024-12-30","open":1984,"high":1991,"low":1983,"close":1991,"volume":1001,"marcap":8660850000},{"date":"2025-01-02","open":1991,"high":1999,"low":1991,"close":1998,"volume":5773,"marcap":8691300000},{"date":"2025-01-03","open":1998,"high":2005,"low":1997,"close":2000,"volume":22686,"marcap":8700000000},{"date":"2025-01-06","open":1999,"high":2000,"low":1995,"close":1998,"volume":10779,"marcap":8691300000},{"date":"2025-01-07","open":1998,"high":1999,"low":1997,"close":1998,"volume":1476,"marcap":8691300000},{"date":"2025-01-08","open":1992,"high":1999,"low":1992,"close":1997,"volume":636,"marcap":8686950000},{"date":"2025-01-09","open":1993,"high":1998,"low":1991,"close":1998,"volume":10559,"marcap":8691300000},{"date":"2025-01-10","open":1997,"high":1999,"low":1997,"close":1997,"volume":2099,"marcap":8686950000},{"date":"2025-01-13","open":1994,"high":1999,"low":1993,"close":1999,"volume":4700,"marcap":8695650000},{"date":"2025-01-14","open":1999,"high":2005,"low":1999,"close":2005,"volume":34396,"marcap":8721750000},{"date":"2025-01-15","open":2005,"high":2005,"low":2000,"close":2005,"volume":15815,"marcap":8721750000},{"date":"2025-01-16","open":2000,"high":2005,"low":1996,"close":1999,"volume":7125,"marcap":8695650000},{"date":"2025-01-17","open":1999,"high":2000,"low":1997,"close":2000,"volume":2776,"marcap":8700000000},{"date":"2025-01-20","open":1999,"high":2000,"low":1994,"close":1998,"volume":1879,"marcap":8691300000},{"date":"2025-01-21","open":1997,"high":1998,"low":1981,"close":1998,"volume":1001,"marcap":8691300000},{"date":"2025-01-22","open":1998,"high":1999,"low":1994,"close":1996,"volume":28193,"marcap":8682600000},{"date":"2025-01-23","open":1996,"high":1998,"low":1987,"close":1997,"volume":4057,"marcap":8686950000},{"date":"2025-01-24","open":1998,"high":1999,"low":1991,"close":1996,"volume":15932,"marcap":8682600000},{"date":"2025-01-31","open":1997,"high":1998,"low":1995,"close":1996,"volume":5959,"marcap":8682600000},{"date":"2025-02-03","open":1996,"high":1998,"low":1994,"close":1996,"volume":26918,"marcap":8682600000},{"date":"2025-02-04","open":1997,"high":1999,"low":1995,"close":1998,"volume":59806,"marcap":8691300000},{"date":"2025-02-05","open":1997,"high":2000,"low":1996,"close":1999,"volume":15815,"marcap":8695650000},{"date":"2025-02-06","open":1998,"high":2005,"low":1998,"close":2005,"volume":13168,"marcap":8721750000},{"date":"2025-02-07","open":2005,"high":2005,"low":2000,"close":2005,"volume":1046,"marcap":8721750000},{"date":"2025-02-10","open":2005,"high":2005,"low":2000,"close":2000,"volume":10582,"marcap":8700000000},{"date":"2025-02-11","open":2000,"high":2005,"low":2000,"close":2000,"volume":1926,"marcap":8700000000},{"date":"2025-02-12","open":2000,"high":2005,"low":2000,"close":2005,"volume":1202,"marcap":8721750000},{"date":"2025-02-13","open":2005,"high":2010,"low":2000,"close":2010,"volume":8908,"marcap":8743500000},{"date":"2025-02-14","open":2005,"high":2010,"low":2000,"close":2005,"volume":15030,"marcap":8721750000},{"date":"2025-02-17","open":2005,"high":2015,"low":2005,"close":2015,"volume":30893,"marcap":8765250000},{"date":"2025-02-18","open":2010,"high":2010,"low":2005,"close":2005,"volume":650,"marcap":8721750000},{"date":"2025-02-19","open":2005,"high":2010,"low":2005,"close":2010,"volume":4009,"marcap":8743500000},{"date":"2025-02-20","open":2010,"high":2015,"low":2005,"close":2010,"volume":2063,"marcap":8743500000},{"date":"2025-02-21","open":2015,"high":2015,"low":2010,"close":2015,"volume":11120,"marcap":8765250000},{"date":"2025-02-24","open":2015,"high":2015,"low":2010,"close":2015,"volume":28660,"marcap":8765250000},{"date":"2025-02-25","open":2015,"high":2020,"low":2010,"close":2020,"volume":32715,"marcap":8787000000},{"date":"2025-02-26","open":2015,"high":2020,"low":2015,"close":2020,"volume":12666,"marcap":8787000000},{"date":"2025-02-27","open":2015,"high":2020,"low":2015,"close":2015,"volume":6276,"marcap":8765250000},{"date":"2025-02-28","open":2015,"high":2020,"low":2015,"close":2015,"volume":5210,"marcap":8765250000},{"date":"2025-03-04","open":2015,"high":2015,"low":2010,"close":2015,"volume":20880,"marcap":8765250000},{"date":"2025-03-05","open":2010,"high":2015,"low":2010,"close":2015,"volume":1794,"marcap":8765250000},{"date":"2025-03-06","open":2015,"high":2020,"low":2015,"close":2015,"volume":4001,"marcap":8765250000},{"date":"2025-03-07","open":2010,"high":2020,"low":2010,"close":2020,"volume":4617,"marcap":8787000000},{"date":"2025-03-10","open":2020,"high":2020,"low":2015,"close":2015,"volume":9538,"marcap":8765250000},{"date":"2025-03-11","open":2015,"high":2015,"low":2005,"close":2010,"volume":4783,"marcap":8743500000},{"date":"2025-03-12","open":2010,"high":2020,"low":2005,"close":2010,"volume":341,"marcap":8743500000},{"date":"2025-03-13","open":2010,"high":2015,"low":2010,"close":2015,"volume":688,"marcap":8765250000},{"date":"2025-03-14","open":2010,"high":2020,"low":2010,"close":2020,"volume":1171,"marcap":8787000000},{"date":"2025-03-17","open":2015,"high":2020,"low":2010,"close":2015,"volume":9290,"marcap":8765250000},{"date":"2025-03-18","open":2015,"high":2015,"low":2005,"close":2010,"volume":2261,"marcap":8743500000},{"date":"2025-03-19","open":2010,"high":2015,"low":2005,"close":2010,"volume":10414,"marcap":8743500000},{"date":"2025-03-20","open":2005,"high":2010,"low":2000,"close":2010,"volume":29384,"marcap":8743500000},{"date":"2025-03-21","open":2010,"high":2010,"low":2005,"close":2010,"volume":885,"marcap":8743500000},{"date":"2025-03-24","open":2010,"high":2015,"low":2000,"close":2010,"volume":2132,"marcap":8743500000},{"date":"2025-03-25","open":2005,"high":2010,"low":2005,"close":2010,"volume":1503,"marcap":8743500000},{"date":"2025-03-26","open":2010,"high":2010,"low":2005,"close":2010,"volume":251,"marcap":8743500000},{"date":"2025-03-27","open":2010,"high":2015,"low":2005,"close":2015,"volume":5948,"marcap":8765250000},{"date":"2025-03-28","open":2010,"high":2015,"low":2010,"close":2015,"volume":7655,"marcap":8765250000},{"date":"2025-03-31","open":2010,"high":2015,"low":2010,"close":2010,"volume":4474,"marcap":8743500000},{"date":"2025-04-01","open":2015,"high":2015,"low":2010,"close":2015,"volume":3904,"marcap":8765250000},{"date":"2025-04-02","open":2010,"high":2020,"low":2010,"close":2020,"volume":10847,"marcap":8787000000},{"date":"2025-04-03","open":2010,"high":2020,"low":2010,"close":2020,"volume":2062,"marcap":8787000000},{"date":"2025-04-04","open":2020,"high":2020,"low":2010,"close":2015,"volume":4119,"marcap":8765250000},{"date":"2025-04-07","open":2010,"high":2015,"low":2005,"close":2015,"volume":9479,"marcap":8765250000},{"date":"2025-04-08","open":2015,"high":2020,"low":2010,"close":2015,"volume":30145,"marcap":8765250000},{"date":"2025-04-09","open":2010,"high":2020,"low":2010,"close":2010,"volume":8098,"marcap":8743500000},{"date":"2025-04-10","open":2005,"high":2020,"low":2000,"close":2020,"volume":5451,"marcap":8787000000},{"date":"2025-04-11","open":2015,"high":2020,"low":2015,"close":2020,"volume":6483,"marcap":8787000000},{"date":"2025-04-14","open":2015,"high":2030,"low":2010,"close":2030,"volume":41380,"marcap":8830500000},{"date":"2025-04-15","open":2020,"high":2030,"low":2020,"close":2030,"volume":16923,"marcap":8830500000},{"date":"2025-04-16","open":2025,"high":2025,"low":2015,"close":2015,"volume":1848,"marcap":8765250000},{"date":"2025-04-17","open":2015,"high":2020,"low":2015,"close":2020,"volume":7800,"marcap":8787000000},{"date":"2025-04-18","open":2015,"high":2020,"low":2015,"close":2020,"volume":12750,"marcap":8787000000},{"date":"2025-04-21","open":2015,"high":2020,"low":2015,"close":2020,"volume":6885,"marcap":8787000000},{"date":"2025-04-22","open":2020,"high":2020,"low":2015,"close":2020,"volume":4032,"marcap":8787000000},{"date":"2025-04-23","open":2020,"high":2025,"low":2020,"close":2025,"volume":9658,"marcap":8808750000},{"date":"2025-04-24","open":2020,"high":2030,"low":2020,"close":2030,"volume":4703,"marcap":8830500000},{"date":"2025-04-25","open":2030,"high":2030,"low":2020,"close":2030,"volume":18647,"marcap":8830500000},{"date":"2025-04-28","open":2015,"high":2030,"low":2015,"close":2025,"volume":29918,"marcap":8808750000},{"date":"2025-04-29","open":2025,"high":2030,"low":2025,"close":2030,"volume":25756,"marcap":8830500000},{"date":"2025-04-30","open":2030,"high":2035,"low":2025,"close":2025,"volume":12670,"marcap":8808750000},{"date":"2025-05-02","open":2025,"high":2040,"low":2025,"close":2040,"volume":15007,"marcap":8874000000},{"date":"2025-05-07","open":2030,"high":2040,"low":2030,"close":2035,"volume":18013,"marcap":8852250000},{"date":"2025-05-08","open":2035,"high":2045,"low":2030,"close":2040,"volume":13774,"marcap":8874000000},{"date":"2025-05-09","open":2045,"high":2050,"low":2045,"close":2050,"volume":2428,"marcap":8917500000},{"date":"2025-05-12","open":2050,"high":2060,"low":2050,"close":2050,"volume":24143,"marcap":8917500000},{"date":"2025-05-13","open":2050,"high":2055,"low":2050,"close":2050,"volume":7095,"marcap":8917500000},{"date":"2025-05-14","open":2045,"high":2055,"low":2045,"close":2055,"volume":686,"marcap":8939250000},{"date":"2025-05-15","open":2045,"high":2065,"low":2045,"close":2065,"volume":17719,"marcap":8982750000},{"date":"2025-05-16","open":2060,"high":2065,"low":2055,"close":2065,"volume":2399,"marcap":8982750000},{"date":"2025-05-19","open":2075,"high":2075,"low":2060,"close":2060,"volume":2982,"marcap":8961000000},{"date":"2025-05-20","open":2060,"high":2080,"low":2060,"close":2070,"volume":4682,"marcap":9004500000},{"date":"2025-05-21","open":2070,"high":2075,"low":2055,"close":2055,"volume":12057,"marcap":8939250000},{"date":"2025-05-22","open":2055,"high":2065,"low":2055,"close":2060,"volume":306,"marcap":8961000000},{"date":"2025-05-23","open":2060,"high":2070,"low":2055,"close":2060,"volume":1142,"marcap":8961000000},{"date":"2025-05-26","open":2065,"high":2080,"low":2060,"close":2075,"volume":13832,"marcap":9026250000},{"date":"2025-05-27","open":2065,"high":2090,"low":2065,"close":2085,"volume":37013,"marcap":9069750000},{"date":"2025-05-28","open":2095,"high":2095,"low":2070,"close":2080,"volume":433,"marcap":9048000000},{"date":"2025-05-29","open":2070,"high":2080,"low":2065,"close":2075,"volume":3671,"marcap":9026250000},{"date":"2025-05-30","open":2065,"high":2075,"low":2060,"close":2070,"volume":1207,"marcap":9004500000},{"date":"2025-06-02","open":2060,"high":2070,"low":2060,"close":2065,"volume":1664,"marcap":8982750000},{"date":"2025-06-04","open":2060,"high":2075,"low":2060,"close":2070,"volume":1253,"marcap":9004500000},{"date":"2025-06-05","open":2080,"high":2080,"low":2070,"close":2075,"volume":2103,"marcap":9026250000},{"date":"2025-06-09","open":2065,"high":2080,"low":2065,"close":2075,"volume":10493,"marcap":9026250000},{"date":"2025-06-10","open":2075,"high":2080,"low":2065,"close":2080,"volume":2507,"marcap":9048000000},{"date":"2025-06-11","open":2070,"high":2080,"low":2065,"close":2080,"volume":3268,"marcap":9048000000},{"date":"2025-06-12","open":2075,"high":2075,"low":2065,"close":2075,"volume":2280,"marcap":9026250000},{"date":"2025-06-13","open":2072,"high":2072,"low":2070,"close":2070,"volume":398,"marcap":9004500000},{"date":"2025-06-16","open":2070,"high":2105,"low":2065,"close":2095,"volume":30392,"marcap":9113250000},{"date":"2025-06-17","open":2090,"high":2090,"low":2075,"close":2085,"volume":330,"marcap":9069750000},{"date":"2025-06-18","open":2085,"high":2085,"low":2070,"close":2085,"volume":824,"marcap":9069750000},{"date":"2025-06-19","open":2080,"high":2085,"low":2075,"close":2075,"volume":368,"marcap":9026250000},{"date":"2025-06-20","open":2075,"high":2075,"low":2060,"close":2060,"volume":11940,"marcap":8961000000},{"date":"2025-06-23","open":2060,"high":2060,"low":2050,"close":2055,"volume":2862,"marcap":8939250000},{"date":"2025-06-24","open":2055,"high":2065,"low":2050,"close":2065,"volume":24516,"marcap":8982750000},{"date":"2025-06-25","open":2055,"high":2070,"low":2055,"close":2070,"volume":124,"marcap":9004500000},{"date":"2025-06-26","open":2075,"high":2075,"low":2075,"close":2075,"volume":126,"marcap":9026250000},{"date":"2025-06-27","open":2075,"high":2080,"low":2070,"close":2080,"volume":9932,"marcap":9048000000},{"date":"2025-06-30","open":2070,"high":2080,"low":2035,"close":2060,"volume":12464,"marcap":8961000000},{"date":"2025-07-01","open":2055,"high":2065,"low":2055,"close":2065,"volume":11515,"marcap":8982750000},{"date":"2025-07-02","open":2060,"high":2065,"low":2060,"close":2065,"volume":75,"marcap":8982750000},{"date":"2025-07-03","open":2060,"high":2060,"low":2055,"close":2060,"volume":704,"marcap":8961000000},{"date":"2025-07-04","open":2055,"high":2060,"low":2050,"close":2060,"volume":1585,"marcap":8961000000},{"date":"2025-07-07","open":2055,"high":2055,"low":2045,"close":2055,"volume":471,"marcap":8939250000},{"date":"2025-07-08","open":2055,"high":2055,"low":2045,"close":2055,"volume":620,"marcap":8939250000},{"date":"2025-07-09","open":2050,"high":2050,"low":2045,"close":2050,"volume":4978,"marcap":8917500000},{"date":"2025-07-10","open":2050,"high":2050,"low":2030,"close":2040,"volume":5636,"marcap":8874000000},{"date":"2025-07-11","open":2035,"high":2040,"low":2030,"close":2040,"volume":7121,"marcap":8874000000},{"date":"2025-07-14","open":2040,"high":2045,"low":2035,"close":2040,"volume":7163,"marcap":8874000000},{"date":"2025-07-15","open":2045,"high":2045,"low":2035,"close":2045,"volume":1912,"marcap":8895750000},{"date":"2025-07-16","open":2050,"high":2050,"low":2035,"close":2040,"volume":2072,"marcap":8874000000},{"date":"2025-07-17","open":2035,"high":2050,"low":2025,"close":2050,"volume":11633,"marcap":8917500000},{"date":"2025-07-18","open":2050,"high":2060,"low":2050,"close":2050,"volume":16897,"marcap":8917500000},{"date":"2025-07-21","open":2035,"high":2050,"low":2035,"close":2050,"volume":4307,"marcap":8917500000},{"date":"2025-07-22","open":2050,"high":2050,"low":2050,"close":2050,"volume":0,"marcap":8917500000},{"date":"2025-07-23","open":2040,"high":2050,"low":2040,"close":2050,"volume":3718,"marcap":8917500000},{"date":"2025-07-24","open":2035,"high":2050,"low":2030,"close":2040,"volume":6632,"marcap":8874000000},{"date":"2025-07-25","open":2040,"high":2045,"low":2030,"close":2045,"volume":12808,"marcap":8895750000},{"date":"2025-07-28","open":2040,"high":2045,"low":2035,"close":2045,"volume":335,"marcap":8895750000},{"date":"2025-07-29","open":2035,"high":2045,"low":2035,"close":2040,"volume":296,"marcap":8874000000},{"date":"2025-07-30","open":2040,"high":2050,"low":2040,"close":2040,"volume":3650,"marcap":8874000000},{"date":"2025-07-31","open":2035,"high":2040,"low":2030,"close":2040,"volume":1697,"marcap":8874000000},{"date":"2025-08-01","open":2037,"high":2040,"low":2035,"close":2040,"volume":773,"marcap":8874000000},{"date":"2025-08-04","open":2030,"high":2035,"low":2030,"close":2030,"volume":1150,"marcap":8830500000},{"date":"2025-08-05","open":2030,"high":2032,"low":2027,"close":2030,"volume":22262,"marcap":8830500000},{"date":"2025-08-06","open":2030,"high":2035,"low":2020,"close":2035,"volume":1857,"marcap":8852250000},{"date":"2025-08-07","open":2025,"high":2035,"low":2025,"close":2030,"volume":230,"marcap":8830500000},{"date":"2025-08-08","open":2025,"high":2030,"low":2025,"close":2030,"volume":600,"marcap":8830500000},{"date":"2025-08-11","open":2035,"high":2035,"low":2020,"close":2035,"volume":1611,"marcap":8852250000},{"date":"2025-08-12","open":2035,"high":2035,"low":2025,"close":2025,"volume":5535,"marcap":8808750000},{"date":"2025-08-13","open":2030,"high":2035,"low":2025,"close":2030,"volume":13905,"marcap":8830500000},{"date":"2025-08-14","open":2020,"high":2030,"low":2020,"close":2030,"volume":5034,"marcap":8830500000},{"date":"2025-08-18","open":2015,"high":2030,"low":2010,"close":2030,"volume":3903,"marcap":8830500000},{"date":"2025-08-19","open":2015,"high":2025,"low":2015,"close":2020,"volume":1667,"marcap":8787000000},{"date":"2025-08-20","open":2020,"high":2020,"low":2015,"close":2020,"volume":7219,"marcap":8787000000},{"date":"2025-08-21","open":2015,"high":2025,"low":2015,"close":2025,"volume":7323,"marcap":8808750000},{"date":"2025-08-22","open":2025,"high":2025,"low":2020,"close":2025,"volume":1901,"marcap":8808750000},{"date":"2025-08-25","open":2020,"high":2020,"low":2015,"close":2020,"volume":3466,"marcap":8787000000},{"date":"2025-08-26","open":2020,"high":2025,"low":2020,"close":2020,"volume":6794,"marcap":8787000000},{"date":"2025-08-27","open":2020,"high":2025,"low":2020,"close":2020,"volume":907,"marcap":8787000000},{"date":"2025-08-28","open":2015,"high":2020,"low":2015,"close":2020,"volume":3950,"marcap":8787000000},{"date":"2025-08-29","open":2020,"high":2025,"low":2020,"close":2020,"volume":150,"marcap":8787000000},{"date":"2025-09-01","open":2020,"high":2025,"low":2015,"close":2020,"volume":3261,"marcap":8787000000},{"date":"2025-09-02","open":2015,"high":2025,"low":2015,"close":2020,"volume":120,"marcap":8787000000},{"date":"2025-09-03","open":2020,"high":2020,"low":2015,"close":2020,"volume":9293,"marcap":8787000000},{"date":"2025-09-04","open":2020,"high":2020,"low":2020,"close":2020,"volume":0,"marcap":8787000000},{"date":"2025-09-05","open":2020,"high":2025,"low":2015,"close":2025,"volume":596,"marcap":8808750000},{"date":"2025-09-08","open":2030,"high":2030,"low":2025,"close":2030,"volume":294,"marcap":8830500000},{"date":"2025-09-09","open":2020,"high":2030,"low":2020,"close":2020,"volume":1043,"marcap":8787000000},{"date":"2025-09-10","open":2020,"high":2045,"low":2020,"close":2035,"volume":223,"marcap":8852250000},{"date":"2025-09-11","open":2025,"high":2025,"low":2020,"close":2025,"volume":3045,"marcap":8808750000},{"date":"2025-09-12","open":2025,"high":2030,"low":2020,"close":2025,"volume":5169,"marcap":8808750000},{"date":"2025-09-15","open":2030,"high":2040,"low":2030,"close":2040,"volume":5696,"marcap":8874000000},{"date":"2025-09-16","open":2030,"high":2040,"low":2030,"close":2040,"volume":4692,"marcap":8874000000},{"date":"2025-09-17","open":2035,"high":2040,"low":2030,"close":2035,"volume":14072,"marcap":8852250000},{"date":"2025-09-18","open":2032,"high":2035,"low":2030,"close":2030,"volume":31362,"marcap":8830500000},{"date":"2025-09-19","open":2030,"high":2030,"low":2030,"close":2030,"volume":387,"marcap":8830500000},{"date":"2025-09-22","open":2035,"high":2040,"low":2020,"close":2040,"volume":8888,"marcap":8874000000},{"date":"2025-09-23","open":2040,"high":2040,"low":2030,"close":2030,"volume":36,"marcap":8830500000},{"date":"2025-09-24","open":2030,"high":2035,"low":2030,"close":2035,"volume":325,"marcap":8852250000},{"date":"2025-09-25","open":2030,"high":2035,"low":2030,"close":2030,"volume":655,"marcap":8830500000},{"date":"2025-09-26","open":2030,"high":2040,"low":2030,"close":2040,"volume":8872,"marcap":8874000000},{"date":"2025-09-29","open":2040,"high":2040,"low":2030,"close":2030,"volume":735,"marcap":8830500000},{"date":"2025-09-30","open":2030,"high":2030,"low":2030,"close":2030,"volume":544,"marcap":8830500000},{"date":"2025-10-01","open":2040,"high":2045,"low":2025,"close":2040,"volume":3186,"marcap":8874000000},{"date":"2025-10-02","open":2040,"high":2040,"low":2035,"close":2040,"volume":195,"marcap":8874000000},{"date":"2025-10-10","open":2035,"high":2045,"low":2035,"close":2040,"volume":3907,"marcap":8874000000},{"date":"2025-10-13","open":2035,"high":2040,"low":2035,"close":2040,"volume":438,"marcap":8874000000},{"date":"2025-10-14","open":2035,"high":2045,"low":2035,"close":2040,"volume":2283,"marcap":8874000000},{"date":"2025-10-15","open":2045,"high":2045,"low":2040,"close":2045,"volume":2860,"marcap":8895750000},{"date":"2025-10-16","open":2040,"high":2050,"low":2040,"close":2045,"volume":11170,"marcap":8895750000},{"date":"2025-10-17","open":2050,"high":2050,"low":2040,"close":2045,"volume":527,"marcap":8895750000},{"date":"2025-10-20","open":2050,"high":2050,"low":2040,"close":2045,"volume":251,"marcap":8895750000},{"date":"2025-10-21","open":2080,"high":2080,"low":2045,"close":2045,"volume":4585,"marcap":8895750000},{"date":"2025-10-22","open":2040,"high":2045,"low":2035,"close":2040,"volume":2423,"marcap":8874000000},{"date":"2025-10-23","open":2040,"high":2055,"low":2040,"close":2055,"volume":2710,"marcap":8939250000},{"date":"2025-10-24","open":2050,"high":2055,"low":2045,"close":2050,"volume":1243,"marcap":8917500000},{"date":"2025-10-27","open":2060,"high":2075,"low":2045,"close":2055,"volume":5897,"marcap":8939250000},{"date":"2025-10-28","open":2050,"high":2065,"low":2045,"close":2060,"volume":6740,"marcap":8961000000},{"date":"2025-10-29","open":2065,"high":2075,"low":2060,"close":2070,"volume":5327,"marcap":9004500000},{"date":"2025-10-30","open":2065,"high":2065,"low":2060,"close":2060,"volume":967,"marcap":8961000000},{"date":"2025-10-31","open":2060,"high":2060,"low":2050,"close":2060,"volume":885,"marcap":8961000000},{"date":"2025-11-03","open":2055,"high":2070,"low":2045,"close":2060,"volume":5568,"marcap":8961000000},{"date":"2025-11-04","open":2060,"high":2060,"low":2045,"close":2060,"volume":3608,"marcap":8961000000},{"date":"2025-11-05","open":2055,"high":2055,"low":2045,"close":2050,"volume":3321,"marcap":8917500000},{"date":"2025-11-06","open":2045,"high":2055,"low":2035,"close":2035,"volume":14068,"marcap":8852250000},{"date":"2025-11-07","open":2040,"high":2045,"low":2035,"close":2045,"volume":1729,"marcap":8895750000},{"date":"2025-11-10","open":2040,"high":2045,"low":2035,"close":2035,"volume":5582,"marcap":8852250000},{"date":"2025-11-11","open":2035,"high":2040,"low":2035,"close":2035,"volume":91,"marcap":8852250000},{"date":"2025-11-12","open":2045,"high":2045,"low":2030,"close":2040,"volume":486,"marcap":8874000000},{"date":"2025-11-13","open":2035,"high":2040,"low":2035,"close":2035,"volume":35,"marcap":8852250000},{"date":"2025-11-14","open":2030,"high":2035,"low":2025,"close":2030,"volume":1489,"marcap":8830500000},{"date":"2025-11-17","open":2035,"high":2035,"low":2035,"close":2035,"volume":470,"marcap":8852250000},{"date":"2025-11-18","open":2040,"high":2040,"low":2030,"close":2035,"volume":1612,"marcap":8852250000},{"date":"2025-11-19","open":2030,"high":2045,"low":2030,"close":2040,"volume":30152,"marcap":8874000000},{"date":"2025-11-20","open":2040,"high":2040,"low":2040,"close":2040,"volume":433,"marcap":8874000000},{"date":"2025-11-21","open":2035,"high":2040,"low":2025,"close":2040,"volume":8123,"marcap":8874000000},{"date":"2025-11-24","open":2025,"high":2045,"low":2025,"close":2040,"volume":1560,"marcap":8874000000},{"date":"2025-11-25","open":2030,"high":2030,"low":2030,"close":2030,"volume":13,"marcap":8830500000},{"date":"2025-11-26","open":2025,"high":2040,"low":2025,"close":2030,"volume":18,"marcap":8830500000},{"date":"2025-11-27","open":2030,"high":2040,"low":2025,"close":2040,"volume":10878,"marcap":8874000000},{"date":"2025-11-28","open":2040,"high":2040,"low":2035,"close":2040,"volume":1919,"marcap":8874000000},{"date":"2025-12-01","open":2040,"high":2045,"low":2040,"close":2040,"volume":651,"marcap":8874000000},{"date":"2025-12-02","open":2035,"high":2065,"low":2035,"close":2065,"volume":17775,"marcap":8982750000},{"date":"2025-12-03","open":2055,"high":2065,"low":2055,"close":2060,"volume":1446,"marcap":8961000000},{"date":"2025-12-04","open":2050,"high":2070,"low":2050,"close":2055,"volume":4388,"marcap":8939250000},{"date":"2025-12-05","open":2065,"high":2345,"low":2050,"close":2055,"volume":204145,"marcap":8939250000},{"date":"2025-12-08","open":2055,"high":2065,"low":2055,"close":2055,"volume":3558,"marcap":8939250000},{"date":"2025-12-09","open":2055,"high":2060,"low":2055,"close":2060,"volume":238,"marcap":8961000000},{"date":"2025-12-10","open":2055,"high":2065,"low":2050,"close":2050,"volume":6906,"marcap":8917500000},{"date":"2025-12-11","open":2060,"high":2060,"low":2045,"close":2045,"volume":12496,"marcap":8895750000},{"date":"2025-12-12","open":2035,"high":2045,"low":2035,"close":2045,"volume":17667,"marcap":8895750000},{"date":"2025-12-15","open":2040,"high":2050,"low":2040,"close":2040,"volume":52460,"marcap":8874000000},{"date":"2025-12-16","open":2035,"high":2295,"low":2035,"close":2045,"volume":154593,"marcap":8895750000},{"date":"2025-12-17","open":2045,"high":2080,"low":2040,"close":2065,"volume":12838,"marcap":8982750000},{"date":"2025-12-18","open":2060,"high":2065,"low":2055,"close":2060,"volume":13608,"marcap":8961000000},{"date":"2025-12-19","open":2050,"high":2060,"low":2045,"close":2060,"volume":3442,"marcap":8961000000},{"date":"2025-12-22","open":2060,"high":2075,"low":2045,"close":2055,"volume":1067,"marcap":8939250000},{"date":"2025-12-23","open":2050,"high":2065,"low":2050,"close":2065,"volume":150,"marcap":8982750000},{"date":"2025-12-24","open":2055,"high":2075,"low":2055,"close":2060,"volume":434,"marcap":8961000000},{"date":"2025-12-26","open":2060,"high":2070,"low":2060,"close":2060,"volume":987,"marcap":8961000000},{"date":"2025-12-29","open":2060,"high":2070,"low":2060,"close":2070,"volume":607,"marcap":9004500000},{"date":"2025-12-30","open":2070,"high":2075,"low":2070,"close":2075,"volume":3969,"marcap":9026250000},{"date":"2026-01-02","open":2070,"high":2070,"low":2060,"close":2070,"volume":121,"marcap":9004500000},{"date":"2026-01-05","open":2065,"high":2070,"low":2055,"close":2070,"volume":3235,"marcap":9004500000},{"date":"2026-01-06","open":2065,"high":2065,"low":2065,"close":2065,"volume":898,"marcap":8982750000},{"date":"2026-01-07","open":2070,"high":2075,"low":2070,"close":2075,"volume":2203,"marcap":9026250000}]}